weerlive/__init__.py
weerlive/exceptions.py
weerlive/models.py
weerlive/py.typed
weerlive/weerlive.py
weerlive-0.2.2.dist-info/LICENSE
weerlive-0.2.2.dist-info/METADATA
weerlive-0.2.2.dist-info/WHEEL
weerlive-0.2.2.dist-info/RECORD
