Metadata-Version: 2.1
Name: weerlive
Version: 0.2.2
Summary: Asynchronous Python client for weather info from Weerlive
Home-page: https://github.com/klaasnicolaas/python-weerlive
License: MIT
Keywords: weerlive,api,async,client,weather
Author: Klaas Schoute
Author-email: hello@student-techlife.com
Maintainer: Klaas Schoute
Maintainer-email: hello@student-techlife.com
Requires-Python: >=3.11,<4.0
Classifier: Framework :: AsyncIO
Classifier: Intended Audience :: Developers
Classifier: License :: OSI Approved :: MIT License
Classifier: Natural Language :: English
Classifier: Programming Language :: Python :: 3
Classifier: Programming Language :: Python :: 3.11
Classifier: Programming Language :: Python :: 3.12
Classifier: Topic :: Software Development :: Libraries :: Python Modules
Requires-Dist: aiohttp (>=3.0.0)
Requires-Dist: mashumaro (>=3.11,<4.0)
Requires-Dist: orjson (>=3.9.10,<4.0.0)
Requires-Dist: yarl (>=1.6.0)
Project-URL: Bug Tracker, https://github.com/klaasnicolaas/python-weerlive/issues
Project-URL: Changelog, https://github.com/klaasnicolaas/python-weerlive/releases
Project-URL: Documentation, https://github.com/klaasnicolaas/python-weerlive
Project-URL: Repository, https://github.com/klaasnicolaas/python-weerlive
